ffmpegio/__init__.py
ffmpegio/_utils.py
ffmpegio/analyze.py
ffmpegio/audio.py
ffmpegio/caps.py
ffmpegio/configure.py
ffmpegio/devices.py
ffmpegio/errors.py
ffmpegio/ffmpegprocess.py
ffmpegio/image.py
ffmpegio/media.py
ffmpegio/path.py
ffmpegio/probe.py
ffmpegio/threading.py
ffmpegio/transcode.py
ffmpegio/video.py
ffmpegio/filtergraph/Chain.py
ffmpegio/filtergraph/Filter.py
ffmpegio/filtergraph/Graph.py
ffmpegio/filtergraph/GraphLinks.py
ffmpegio/filtergraph/__init__.py
ffmpegio/filtergraph/abc.py
ffmpegio/filtergraph/build.py
ffmpegio/filtergraph/convert.py
ffmpegio/filtergraph/exceptions.py
ffmpegio/filtergraph/typing.py
ffmpegio/filtergraph/util.py
ffmpegio/plugins/__init__.py
ffmpegio/plugins/finder_ffdl.py
ffmpegio/plugins/finder_static.py
ffmpegio/plugins/finder_syspath.py
ffmpegio/plugins/finder_win32.py
ffmpegio/plugins/hookspecs.py
ffmpegio/plugins/rawdata_bytes.py
ffmpegio/plugins/rawdata_mpl.py
ffmpegio/plugins/rawdata_numpy.py
ffmpegio/plugins/devices/__init__.py
ffmpegio/plugins/devices/dshow.py
ffmpegio/streams/AviStreams.py
ffmpegio/streams/SimpleStreams.py
ffmpegio/streams/__init__.py
ffmpegio/utils/__init__.py
ffmpegio/utils/avi.py
ffmpegio/utils/concat.py
ffmpegio/utils/filter.py
ffmpegio/utils/log.py
ffmpegio/utils/parser.py
ffmpegio/utils/typing.py
ffmpegio_core-0.11.0.dist-info/LICENSE
ffmpegio_core-0.11.0.dist-info/METADATA
ffmpegio_core-0.11.0.dist-info/WHEEL
ffmpegio_core-0.11.0.dist-info/top_level.txt
ffmpegio_core-0.11.0.dist-info/RECORD
